netrun/__init__.py
netrun/py.typed
netrun_core-1.0.0.dist-info/METADATA
netrun_core-1.0.0.dist-info/WHEEL
netrun_core-1.0.0.dist-info/licenses/LICENSE
netrun_core-1.0.0.dist-info/RECORD
