Metadata-Version: 2.4
Name: netrun-core
Version: 1.0.0
Summary: Netrun Systems namespace package foundation - provides the unified 'netrun' namespace for all Netrun packages
Project-URL: Homepage, https://netrunsystems.com
Project-URL: Documentation, https://docs.netrunsystems.com
Project-URL: Repository, https://github.com/netrunsystems/netrun-service-library
Author-email: Netrun Systems <dev@netrunsystems.com>, Daniel Garza <daniel@netrunsystems.com>
License: MIT
License-File: LICENSE
Keywords: enterprise,fastapi,foundation,namespace,netrun
Classifier: Development Status :: 5 - Production/Stable
Classifier: Framework :: FastAPI
Classifier: Intended Audience :: Developers
Classifier: License :: OSI Approved :: MIT License
Classifier: Programming Language :: Python :: 3
Classifier: Programming Language :: Python :: 3.10
Classifier: Programming Language :: Python :: 3.11
Classifier: Programming Language :: Python :: 3.12
Classifier: Topic :: Software Development :: Libraries :: Python Modules
Classifier: Typing :: Typed
Requires-Python: >=3.10
